Metadata-Version: 2.4
Name: shodo_ssg
Version: 0.0.dev4
Summary: A Python-based static site generator for building sites from Markdown and JSON files
Author-email: Ryan Phillips <ryanphillipssoftware@gmail.com>
License: MIT
Project-URL: homepage, https://shodo.dev
Project-URL: source, https://github.com/ryanmphill/shodo-static-gen
Project-URL: issues, https://github.com/ryanmphill/shodo-static-gen/issues
Project-URL: documentation, https://shodo.dev/docs
Keywords: shodo,static site generator,ssg,blog,rss
Classifier: Programming Language :: Python :: 3
Classifier: Programming Language :: Python :: 3.9
Classifier: Programming Language :: Python :: 3.10
Classifier: Programming Language :: Python :: 3.11
Classifier: Programming Language :: Python :: 3.12
Classifier: Programming Language :: Python :: 3.13
Classifier: Programming Language :: Python :: 3.14
Classifier: License :: OSI Approved :: MIT License
Classifier: Operating System :: OS Independent
Classifier: Intended Audience :: Developers
Classifier: Topic :: Internet
Classifier: Topic :: Software Development
Classifier: Topic :: Software Development :: Build Tools
Classifier: Topic :: Software Development :: Libraries
Classifier: Topic :: Software Development :: Libraries :: Application Frameworks
Classifier: Topic :: Text Processing :: Markup :: Markdown
Classifier: Topic :: Text Processing :: Markup :: HTML
Classifier: Topic :: Software Development :: Libraries :: Python Modules
Classifier: Topic :: Software Development :: Code Generators
Classifier: Topic :: Internet :: WWW/HTTP :: Site Management
Requires-Python: >=3.9
License-File: LICENSE
Requires-Dist: Jinja2>=3.1.3
Requires-Dist: markdown2>=2.4.13
Requires-Dist: markupsafe>=2.1.5
Provides-Extra: dev
Requires-Dist: black; extra == "dev"
Requires-Dist: pytest; extra == "dev"
Dynamic: license-file
